pyixapi/__init__.py
pyixapi/core/__init__.py
pyixapi/core/api.py
pyixapi/core/endpoint.py
pyixapi/core/query.py
pyixapi/core/response.py
pyixapi/core/token.py
pyixapi/core/util.py
pyixapi/models.py
pyixapi-0.2.6.dist-info/LICENSE
pyixapi-0.2.6.dist-info/METADATA
pyixapi-0.2.6.dist-info/WHEEL
pyixapi-0.2.6.dist-info/RECORD
