Metadata-Version: 2.3
Name: pyixapi
Version: 0.2.6
Summary: Python API client library for IX-API
License: Apache-2.0
Author: Guillaume Mazoyer
Author-email: oss@mazoyer.eu
Requires-Python: >=3.9
Classifier: Intended Audience :: Developers
Classifier: Programming Language :: Python :: 3
Classifier: Programming Language :: Python :: 3.9
Classifier: Programming Language :: Python :: 3.10
Classifier: Programming Language :: Python :: 3.11
Classifier: Programming Language :: Python :: 3.12
Classifier: Programming Language :: Python :: 3.13
Provides-Extra: dev
Requires-Dist: PyJWT (>=2.4.0,<2.11)
Requires-Dist: pytest ; extra == "dev"
Requires-Dist: requests (>=2.20.0,<3.0)
Requires-Dist: ruff (>=0.9,<0.10) ; extra == "dev"
